devicev1/__init__.py
devicev1/device_test.py
devicev1/client/__init__.py
devicev1/client/device_api.py
devicev1/client/device_client.py
devicev1/tools/__init__.py
devicev1/tools/update_device.py
windmill_device-1.0.0.19.dist-info/METADATA
windmill_device-1.0.0.19.dist-info/WHEEL
windmill_device-1.0.0.19.dist-info/top_level.txt
windmill_device-1.0.0.19.dist-info/RECORD
